CHANGELOG.md
jommerce/__init__.py
jommerce/__main__.py
jommerce/auth/__init__.py
jommerce/auth/admin.py
jommerce/auth/apps.py
jommerce/auth/conf.py
jommerce/auth/forms.py
jommerce/auth/hashers.py
jommerce/auth/middleware.py
jommerce/auth/migrations/0001_initial.py
jommerce/auth/migrations/0002_session_data.py
jommerce/auth/migrations/0003_session_expire_date.py
jommerce/auth/migrations/0004_session_ip.py
jommerce/auth/migrations/0005_user_status.py
jommerce/auth/migrations/__init__.py
jommerce/auth/models.py
jommerce/auth/settings.py
jommerce/auth/templates/auth/login.html
jommerce/auth/templates/auth/logout.html
jommerce/auth/templates/auth/signup.html
jommerce/auth/urls.py
jommerce/auth/utils.py
jommerce/auth/validators/__init__.py
jommerce/auth/validators/password.py
jommerce/auth/validators/username.py
jommerce/auth/views.py
jommerce/blog/__init__.py
jommerce/blog/admin.py
jommerce/blog/apps.py
jommerce/blog/managers.py
jommerce/blog/migrations/0001_initial.py
jommerce/blog/migrations/0002_category_post_category_and_more.py
jommerce/blog/migrations/__init__.py
jommerce/blog/models.py
jommerce/blog/templates/blog/index.html
jommerce/blog/templates/blog/post.html
jommerce/blog/urls.py
jommerce/blog/views.py
jommerce/jommerce.toml
jommerce/project/__init__.py
jommerce/project/asgi.py
jommerce/project/settings/__init__.py
jommerce/project/settings/base.py
jommerce/project/settings/dev.py
jommerce/project/settings/prod.py
jommerce/project/settings/test.py
jommerce/project/static/css/styles.css
jommerce/project/static/js/scripts.js
jommerce/project/templates/base.html
jommerce/project/templates/index.html
jommerce/project/urls.py
jommerce/project/wsgi.py
jommerce/project_template/.gitignore
jommerce/project_template/manage.py
jommerce/project_template/project_name/__init__.py
jommerce/project_template/project_name/asgi.py
jommerce/project_template/project_name/settings/__init__.py
jommerce/project_template/project_name/settings/base.py
jommerce-3.0.0.dist-info/entry_points.txt
jommerce-3.0.0.dist-info/LICENSE
jommerce-3.0.0.dist-info/METADATA
jommerce-3.0.0.dist-info/WHEEL
jommerce-3.0.0.dist-info/RECORD
