Metadata-Version: 2.1
Name: jommerce
Version: 3.0.0
Summary: A collection of Django apps
Home-page: https://github.com/jommerce/jommerce
License: MIT
Keywords: django,jommerce,extra,contrib
Author: githashem
Author-email: PersonalHashem@gmail.com
Requires-Python: >=3.8,<4.0
Classifier: Environment :: Web Environment
Classifier: Framework :: Django
Classifier: Framework :: Django :: 4.0
Classifier: License :: OSI Approved :: MIT License
Classifier: Programming Language :: Python
Classifier: Programming Language :: Python :: 3
Classifier: Programming Language :: Python :: 3.8
Classifier: Programming Language :: Python :: 3.9
Classifier: Programming Language :: Python :: 3.10
Classifier: Programming Language :: Python :: 3.11
Classifier: Programming Language :: Python :: 3
Classifier: Programming Language :: Python :: 3 :: Only
Classifier: Programming Language :: Python :: 3.10
Classifier: Programming Language :: Python :: 3.11
Classifier: Programming Language :: Python :: 3.8
Classifier: Programming Language :: Python :: 3.9
Classifier: Topic :: Software Development :: Build Tools
Classifier: Topic :: Software Development :: Libraries :: Python Modules
Requires-Dist: Django (>=4.0.3,<5.0.0)
Requires-Dist: django-ipware (>=4.0.2,<5.0.0)
Project-URL: Repository, https://github.com/jommerce/jommerce
